{"392": {"date_utc": "2015-09-26 07:21:10", "files_meta": [{"width": 599, "height": 402}], "title": "59cab-82087_gal", "wordpress_user_name": "renewangtw", "files": ["/2011/11/59cab-82087_gal.jpg"]}, "403": {"date_utc": "2015-09-26 07:21:10", "files_meta": [{"width": 599, "height": 356}], "title": "402d1-82098_gal", "wordpress_user_name": "renewangtw", "files": ["/2011/11/402d1-82098_gal.jpg"]}, "414": {"date_utc": "2015-09-26 07:21:11", "files_meta": [{"width": 600, "height": 450}], "title": "edecb-82090_gal", "wordpress_user_name": "renewangtw", "files": ["/2011/11/edecb-82090_gal.jpg"]}}